git_repo_language_trends/__init__.py
git_repo_language_trends/__main__.py
git_repo_language_trends/_internal/__init__.py
git_repo_language_trends/_internal/args.py
git_repo_language_trends/_internal/main.py
git_repo_language_trends/_internal/matplotlib_output.py
git_repo_language_trends/_internal/output.py
git_repo_language_trends/_internal/progress.py
git_repo_language_trends/_internal/separated_values_output.py
git_repo_language_trends/_internal/utils.py
git_repo_language_trends-0.5.1.dist-info/LICENSE
git_repo_language_trends-0.5.1.dist-info/METADATA
git_repo_language_trends-0.5.1.dist-info/WHEEL
git_repo_language_trends-0.5.1.dist-info/entry_points.txt
git_repo_language_trends-0.5.1.dist-info/top_level.txt
git_repo_language_trends-0.5.1.dist-info/RECORD
