Metadata-Version: 2.1
Name: git-repo-language-trends
Version: 0.5.1
Summary: Analyze programming language usage over time in a git repository and produce a graphical or textual representation of the result.
Home-page: https://github.com/Enselic/git-repo-language-trends
Author: Martin Nordholts
Author-email: enselic@gmail.com
Project-URL: Bug Tracker, https://github.com/Enselic/git-repo-language-trends/issues
Classifier: Programming Language :: Python :: 3
Classifier: License :: OSI Approved :: MIT License
Classifier: Operating System :: OS Independent
Requires-Python: >=3.6
License-File: LICENSE
Requires-Dist: pygit2>=1.2
Requires-Dist: matplotlib>=3.1
